[
  {
    "rn": "akayabu",
    "en": ""
  },
  {
    "rn": "babika arakina na karabaye",
    "en": ""
  },
  {
    "rn": "bamire na banuma bagiye gukora",
    "en": ""
  },
  {
    "rn": "bamire na mama bagiye gukora",
    "en": ""
  },
  {
    "rn": "berahino ahereje umuhoro gatogato",
    "en": ""
  },
  {
    "rn": "berahino arakina na basabose",
    "en": ""
  },
  {
    "rn": "berahino arakina na bayaga",
    "en": ""
  },
  {
    "rn": "berahino yikoreye igiti",
    "en": ""
  },
  {
    "rn": "buname agiye kuvoma",
    "en": ""
  },
  {
    "rn": "buname aherekeje digiri",
    "en": ""
  },
  {
    "rn": "data aje yikoreye igiti",
    "en": ""
  },
  {
    "rn": "data na banuma bagiye gukora",
    "en": ""
  },
  {
    "rn": "data na mama bagiye gukora",
    "en": ""
  },
  {
    "rn": "i muhira hariho akayabu gatoyi. kari n'utuguru tubiri n'utuboko tubiri. kari n'amabara yera n'ayirabura. karakina n'utubeba dutoduto, ariko iyo gahuye n'ibibeba bininibinini, karabibona kagatuna, kakabimira. iyo hari abana batoyi karakina na bo. karabirukana, kakabaharura ku maboko no ku maguru. bano bana hari aho barira ariko bakaguma bakina na ko. iyo data agiye gukama, karamukurikira. aragaha amata, kakayagotomera.",
    "en": ""
  },
  {
    "rn": "mama afise isuka ku rutugu",
    "en": ""
  },
  {
    "rn": "Umuhoro",
    "en": ""
  },
  {
    "rn": "Umusi mwiza",
    "en": "A good day"
  }
]